[{
  "_id": {
    "$oid": "61a3b081afcfae3b5c9df498"
  },
  "cost": 20000,
  "image": "https://th.bing.com/th/id/OIP.eaUkdivTED0KbxsXhyjwzwHaF2?w=274&h=216&c=7&r=0&o=5&dpr=1.25&pid=1.7",
  "description": "With the development of the era, around 2013, various factories have continuously launched medium-frame wheels: Campagnolo Bora 35, Fulcrum Racing Speed 35, Shimano Dura-ACE C35, etc. After several years of developing carbon fiber rim technology, the average high-frame wheel weighs almost as much as a low-frame off-road bike wheel, but it has better aerodynamic performance, which can take into account journeys on flat roads",
  "name": "Fulcrum Racing Light xlr, Shimano Dura-ACE C24",
  "isDelete": true,
  "__v": 0,
  "name_lower": "fulcrum racing light xlr, shimano dura-ace c24"
},{
  "_id": {
    "$oid": "61a5948741bf1cedb0570330"
  },
  "cost": 25000,
  "image": "https://cdn.tgdd.vn/Files/2021/07/20/1369474/phan-loai-cac-dong-xe-dap-pho-bien-tren-thi-5.png",
  "description": "Sau một tuần làm việc, học tập mệt mỏi và căng thẳng. Những phút giây thoải mái và lãng mạn bên những người mình yêu thương trên những chiếc ” XE ĐẠP ĐÔI ” xung quanh “HỒ TÂY” Gió Lồng lộng, Hương SEN thơm mát …..sẽ thật thoải mái và Hạnh phúc.",
  "name": "xe đạp đôi",
  "isDelete": true,
  "__v": 0,
  "name_lower": "xe đạp đôi"
},{
  "_id": {
    "$oid": "61ae2f15d6c44d8a7601a792"
  },
  "cost": 20000,
  "image": "https://cdn.tgdd.vn/Files/2021/07/20/1369474/phan-loai-cac-dong-xe-dap-pho-bien-tren-thi-1.jpg",
  "description": "Xe đạp đường phố là sự kết hợp giữa xe đạp đua và xe đạp địa hình, được thiết kế đa chức năng, có thể đạp ở trong nội thành và cả ngoại thành. Với thiết kế thanh mảnh, lốp xe êm, đồng thời xe được trang bị hệ thống giảm xóc ở phía trước.\n\nSo với xe đạp địa hình thì xe đạp đường phố có tốc độ lớn hơn, so với xe đạp đua thì tư thế ngồi cũng dễ chịu hơn nhiều",
  "name": "Xe đạp đường phố 26 Beauty",
  "name_lower": "xe đạp đường phố 26 beauty",
  "isDelete": true,
  "__v": 0
},{
  "_id": {
    "$oid": "61ae2f87d6c44d8a7601a796"
  },
  "cost": 15000,
  "image": "https://cdn.tgdd.vn/Files/2021/07/20/1369474/phan-loai-cac-dong-xe-dap-pho-bien-tren-thi-6.jpg",
  "description": "Dòng xe này đa phần nữ sử dụng, phục vụ cho việc đi chợ, đưa đón trẻ em trên những đoạn đường ngắn. Ngoài ra, xe đạp đường phố mini cũng giúp chị em phụ nữ trong việc đi dạo, luyện tập thể thao nâng cao sức khỏe",
  "name": "Xe đạp đường phố mini",
  "name_lower": "xe đạp đường phố mini",
  "isDelete": false,
  "__v": 0
},{
  "_id": {
    "$oid": "61ae2fced6c44d8a7601a79a"
  },
  "cost": 25000,
  "image": "https://cdn.tgdd.vn/Files/2021/07/20/1369474/phan-loai-cac-dong-xe-dap-pho-bien-tren-thi-7.png",
  "description": "Xe đạp gấp là một trong những dòng xe đạp thể thao được thiết kế đơn giản, theo cơ chế thông minh. Dòng xe này thường có tính năng sử dụng linh hoạt, kiểu dáng gọn nhẹ, thiết kế mắt mắt đa dạng mẫu mã, đặc biệt khi sử dụng xong bạn có thể xếp lại, tiết kiệm được không gian chỗ để.",
  "name": "Xe đạp gấp",
  "name_lower": "xe đạp gấp",
  "isDelete": false,
  "__v": 0
},{
  "_id": {
    "$oid": "61ae3011d6c44d8a7601a79e"
  },
  "cost": 15000,
  "image": "https://cdn.tgdd.vn/Files/2021/07/20/1369474/phan-loai-cac-dong-xe-dap-pho-bien-tren-thi-7.jpg",
  "description": "Xe đạp cào cào có thiết kế đậm chất thể thao dành cho nam giới, người dùng có thể sử dụng xe đạp để đi làm, đi dạo phố, hay đi phượt trên trên những con đường bằng phẳng đến những địa hình gồ ghề, núi có độ dóc nhẹ.",
  "name": "Xe đạp cào cào",
  "name_lower": "xe đạp cào cào",
  "isDelete": false,
  "__v": 0
},{
  "_id": {
    "$oid": "61b60f9318ba8ae09ca54485"
  },
  "cost": 20000,
  "image": "https://imagizer.imageshack.com/v2/726x484q90/r/922/ajFfPx.jpg",
  "description": "test",
  "name": "testttt",
  "name_lower": "testttt",
  "isDelete": true,
  "img": "images\\WIN_20211212_16_07_12_Pro.jpg",
  "__v": 0
},{
  "_id": {
    "$oid": "61b77f7d4595c37affc3fea0"
  },
  "cost": 20000,
  "image": "https://cdn.shopify.com/s/files/1/2081/1519/products/1600x1067_US_B_Mint_PROFILE-X2.jpg?v=1590502980",
  "description": "Xe đi êm, thích hợp tập thể dục thể thao",
  "name": "Xe 2 bánh ",
  "name_lower": "xe 2 bánh ",
  "isDelete": false,
  "__v": 0
},{
  "_id": {
    "$oid": "61b780224595c37affc3fed1"
  },
  "cost": 20000,
  "image": "https://kenh14cdn.com/thumb_w/660/2017/2373545713584488009515432111733942250897408n-1514196978625.jpg",
  "description": "Chạy bằng 4 bánh nhưng không chèo lên được.",
  "name": "Xe đạp 4 bánh",
  "name_lower": "xe đạp 4 bánh",
  "isDelete": true,
  "__v": 0
},{
  "_id": {
    "$oid": "61b783834595c37affc3fff5"
  },
  "cost": 100000,
  "image": "https://kenh14cdn.com/thumb_w/660/2017/2373545713584488009515432111733942250897408n-1514196978625.jpg",
  "description": "Chó Shiba",
  "name": "Chó Shiba",
  "name_lower": "chó shiba",
  "isDelete": true,
  "__v": 0
},{
  "_id": {
    "$oid": "61b7904f4333e3419fc0a2b3"
  },
  "cost": 20000,
  "image": "http://thegioixehaibanh.com/imgs/xe-dap-dia-hinh-Mountain-Bike-58.jpg",
  "description": "Dòng xe địa hình (Mountain-Bike) hay xe đạp leo núi có trọng lượng khá là nặng, bánh xe to có đường kính khoảng 650 – 700c, nhiều gai, thích hợp để đi trên địa hình gồ ghề như đường dốc, đổ đèo hay đường rừng. Khung to, có phuộc trước và sau, một số loại có lắp giảm shock ở phần giữa xe, ghi đông thiết kế thẳng.",
  "name": "Xe đạp địa hình (Mountain-Bike)",
  "name_lower": "xe đạp địa hình (mountain-bike)",
  "isDelete": false,
  "__v": 0
},{
  "_id": {
    "$oid": "61b7e3a277345065a7ae339b"
  },
  "cost": 20000,
  "image": "asd",
  "description": "De Test",
  "name": "Testtttttttttttttttttt",
  "name_lower": "testtttttttttttttttttt",
  "isDelete": true,
  "__v": 0
},{
  "_id": {
    "$oid": "61b7f5f077345065a7ae3784"
  },
  "cost": 100000,
  "image": "https://ae01.alicdn.com/kf/HTB1ZbR1lv5TBuNjSspmq6yDRVXal/E-BIKE-Munro-2-0-Xe-M-y-i-n-48V-Pin-Lithium-Cao-C-p.jpg_Q90.jpg_.webp",
  "description": "Xe máy 2 bánh",
  "name": "Xe máy",
  "name_lower": "xe máy",
  "isDelete": true,
  "__v": 0
},{
  "_id": {
    "$oid": "61befca3a9f6263e0f492485"
  },
  "cost": 100000,
  "image": "https://xiaomiviet.vn/wp-content/uploads/2019/08/xiaomiviet.vn-xe-dap-dien-tro-luc-xiaomi-himo-c20-xe-dap-dien-tro-luc-xiaomi-himo-c20.jpg",
  "description": "MUi",
  "name": "Xe đạp trợ lực",
  "name_lower": "xe đạp trợ lực",
  "isDelete": true,
  "__v": 0
},{
  "_id": {
    "$oid": "61befdeaa9f6263e0f492539"
  },
  "cost": 10000,
  "image": "https://xiaomiviet.vn/wp-content/uploads/2019/08/xiaomiviet.vn-xe-dap-dien-tro-luc-xiaomi-himo-c20-xe-dap-dien-tro-luc-xiaomi-himo-c20.jpg",
  "description": "Xe đi nhanh hơn .....",
  "name": "Xe trợ lực",
  "name_lower": "xe trợ lực",
  "isDelete": false,
  "__v": 0
},{
  "_id": {
    "$oid": "61c99210c8ef367ba7839af2"
  },
  "cost": 10000,
  "image": "https://cdn.bandeck.com/61139232b26694257cf8ef373a39e9cc",
  "description": "Khung xe đạp lai giống xe đạp địa hình nhưng thiết kế gọn hơn để giảm trọng lượng, tay lái ngang, bánh trước của xe đạp trang bị phuộc giảm xóc, phần yên xe rộng rãi và thoải mái hơn cho phép người lái di chuyển được những quãng đường dài mà không bị mỏi",
  "name": "xe đạp lai",
  "name_lower": "xe đạp lai",
  "isDelete": false,
  "__v": 0
},{
  "_id": {
    "$oid": "61c9bbf0e8a8c9f1d995be68"
  },
  "cost": 10000,
  "image": "https://cdn.bandeck.com/040249296b3a4f880aafa985e9d5d5fc",
  "description": "Xe đạp thăng bằng phù hợp với các bé có độ tuổi từ 18 tháng tuổi trở lên, đây là độ tuổi các trẻ đang tập đi.",
  "name": "Xe đạp trẻ em",
  "name_lower": "xe đạp trẻ em",
  "isDelete": false,
  "__v": 0
},{
  "_id": {
    "$oid": "61da91b80cae6cbf23c19c01"
  },
  "cost": 102365,
  "image": "https://cdn.bandeck.com/8ba750cab099ff6a10b237a5f0d71071",
  "description": "hi hi ha ha he he",
  "name": "Xe đạp trẻ con hihi",
  "name_lower": "xe đạp trẻ con hihi",
  "isDelete": false,
  "__v": 0
},{
  "_id": {
    "$oid": "61dae2fadeb60eb7374e4439"
  },
  "cost": 20000,
  "image": "https://cdn.bandeck.com/4165c7c891bc331756bd6117901218b8",
  "description": "Xe Đạp MTB Giant Hunter 2.0 2020 là mẫu xe được yêu thích nhất hiện nay với thiết kế khung nhôm cao cấp cùng với bộ chuyền động cao cấp giúp xe thay đổi tốc độ nhanh hơn. Xe có gacbaga và chắn bùn theo hãng tiện lợi cho việc đi lại đường dài.",
  "name": "Xe đạp MTB",
  "name_lower": "xe đạp mtb",
  "isDelete": false,
  "__v": 0
},{
  "_id": {
    "$oid": "61dae5dddeb60eb7374e44f1"
  },
  "cost": 20000,
  "image": "https://cdn.bandeck.com/c689e92845b6cb3fc333117ddffa0d43",
  "description": "Giúp bạn di chuyển nhẹ nhàng hơn",
  "name": "Xe đạp trợ lực",
  "name_lower": "xe đạp trợ lực",
  "isDelete": true,
  "__v": 0
},{
  "_id": {
    "$oid": "61dae5dddeb60eb7374e44f5"
  },
  "cost": 20000,
  "image": "https://cdn.bandeck.com/c689e92845b6cb3fc333117ddffa0d43",
  "description": "Giúp bạn di chuyển nhẹ nhàng hơn",
  "name": "Xe đạp trợ lực",
  "name_lower": "xe đạp trợ lực",
  "isDelete": true,
  "__v": 0
},{
  "_id": {
    "$oid": "61dae5e3deb60eb7374e44f9"
  },
  "cost": 20000,
  "image": "https://cdn.bandeck.com/c689e92845b6cb3fc333117ddffa0d43",
  "description": "Giúp bạn di chuyển nhẹ nhàng hơn",
  "name": "Xe đạp trợ lực",
  "name_lower": "xe đạp trợ lực",
  "isDelete": true,
  "__v": 0
},{
  "_id": {
    "$oid": "61dae5e5deb60eb7374e44fd"
  },
  "cost": 20000,
  "image": "https://cdn.bandeck.com/c689e92845b6cb3fc333117ddffa0d43",
  "description": "Giúp bạn di chuyển nhẹ nhàng hơn",
  "name": "Xe đạp trợ lực",
  "name_lower": "xe đạp trợ lực",
  "isDelete": true,
  "__v": 0
},{
  "_id": {
    "$oid": "61dae5e5deb60eb7374e4501"
  },
  "cost": 20000,
  "image": "https://cdn.bandeck.com/c689e92845b6cb3fc333117ddffa0d43",
  "description": "Giúp bạn di chuyển nhẹ nhàng hơn",
  "name": "Xe đạp trợ lực",
  "name_lower": "xe đạp trợ lực",
  "isDelete": true,
  "__v": 0
},{
  "_id": {
    "$oid": "61dae5e5deb60eb7374e4505"
  },
  "cost": 20000,
  "image": "https://cdn.bandeck.com/c689e92845b6cb3fc333117ddffa0d43",
  "description": "Giúp bạn di chuyển nhẹ nhàng hơn",
  "name": "Xe đạp trợ lực",
  "name_lower": "xe đạp trợ lực",
  "isDelete": true,
  "__v": 0
},{
  "_id": {
    "$oid": "61dae5e5deb60eb7374e4509"
  },
  "cost": 20000,
  "image": "https://cdn.bandeck.com/c689e92845b6cb3fc333117ddffa0d43",
  "description": "Giúp bạn di chuyển nhẹ nhàng hơn",
  "name": "Xe đạp trợ lực",
  "name_lower": "xe đạp trợ lực",
  "isDelete": true,
  "__v": 0
},{
  "_id": {
    "$oid": "61dae5ebac63414e9162dc96"
  },
  "cost": 20000,
  "image": "https://cdn.bandeck.com/a23391cb607a483104cbdd17d8b23257",
  "description": "Giúp bạn di chuyển nhẹ nhàng hơn",
  "name": "Xe đạp trợ lực",
  "name_lower": "xe đạp trợ lực",
  "isDelete": true,
  "__v": 0
},{
  "_id": {
    "$oid": "61dae5ecac63414e9162dc9a"
  },
  "cost": 20000,
  "image": "https://cdn.bandeck.com/c689e92845b6cb3fc333117ddffa0d43",
  "description": "Giúp bạn di chuyển nhẹ nhàng hơn",
  "name": "Xe đạp trợ lực",
  "name_lower": "xe đạp trợ lực",
  "isDelete": true,
  "__v": 0
},{
  "_id": {
    "$oid": "61dae5ecac63414e9162dc9e"
  },
  "cost": 20000,
  "image": "https://cdn.bandeck.com/c689e92845b6cb3fc333117ddffa0d43",
  "description": "Giúp bạn di chuyển nhẹ nhàng hơn",
  "name": "Xe đạp trợ lực",
  "name_lower": "xe đạp trợ lực",
  "isDelete": true,
  "__v": 0
},{
  "_id": {
    "$oid": "61dae5eeac63414e9162dca4"
  },
  "cost": 20000,
  "image": "https://cdn.bandeck.com/c689e92845b6cb3fc333117ddffa0d43",
  "description": "Giúp bạn di chuyển nhẹ nhàng hơn",
  "name": "Xe đạp trợ lực",
  "name_lower": "xe đạp trợ lực",
  "isDelete": true,
  "__v": 0
},{
  "_id": {
    "$oid": "61dae5efac63414e9162dca8"
  },
  "cost": 20000,
  "image": "https://cdn.bandeck.com/c3e7ad77a9cc4889f83c403ca6c87178",
  "description": "Giúp bạn di chuyển nhẹ nhàng hơn",
  "name": "Xe đạp trợ lực",
  "name_lower": "xe đạp trợ lực",
  "isDelete": true,
  "__v": 0
},{
  "_id": {
    "$oid": "61dae5efac63414e9162dcac"
  },
  "cost": 20000,
  "image": "https://cdn.bandeck.com/c689e92845b6cb3fc333117ddffa0d43",
  "description": "Giúp bạn di chuyển nhẹ nhàng hơn",
  "name": "Xe đạp trợ lực",
  "name_lower": "xe đạp trợ lực",
  "isDelete": true,
  "__v": 0
},{
  "_id": {
    "$oid": "61daeb63ac63414e9162df5d"
  },
  "cost": 20000,
  "image": "https://cdn.bandeck.com/ea5b97283f4b63008171f7197b77ba52",
  "description": "Xe Đạp Thể Thao Fornix FX26 2021 là một mẫu xe đạp địa hình được làm từ khung thép với những chi tiết được thiết kế ấn tượng. Chiếc xe sử dụng bộ truyền tốc 21 tốc giúp bạn chuyển số linh hoạt hơn. ",
  "name": "Xe Đạp Thể Thao Fornix",
  "name_lower": "xe đạp thể thao fornix",
  "isDelete": false,
  "__v": 0
},{
  "_id": {
    "$oid": "61daec38ac63414e9162e02e"
  },
  "cost": 30000,
  "image": "https://cdn.bandeck.com/84ad6b9283b204f58ce0db19685e21c3",
  "description": "Xe Đạp Thể Thao Galaxy ML200 2021 Vành 26 là mẫu xe mới nhất được hãng cải tiến nhiều về cấu hình cũng như thêm màu sắc cam đen độc đáo, xe Galaxy Ml200 được thiết kế khung hợp kim nhôm kết hợp bộ truyền động Shimano đến từ Nhật giúp xe thay đổi tốc độ tốt hơn và có kèm hệ thống phanh an toàn chắc chắn, chế độ bảo hành lâu dài hậu mãi giúp các bác yên tâm hơn sử dụng.",
  "name": "Xe Đạp Thể Thao Galaxy ML200 2021 Vành 26",
  "name_lower": "xe đạp thể thao galaxy ml200 2021 vành 26",
  "isDelete": false,
  "__v": 0
},{
  "_id": {
    "$oid": "61dc5309368d019deda306d0"
  },
  "cost": 255555,
  "image": "https://cdn.bandeck.com/5ffbfc6ecb3b663453ac956c8c7b5f3b",
  "description": "ddd",
  "name": "aa",
  "name_lower": "aa",
  "isDelete": true,
  "__v": 0
},{
  "_id": {
    "$oid": "61dc5383368d019deda31d79"
  },
  "cost": 5539,
  "image": "https://cdn.bandeck.com/7b28967fdc99489f0645d0cfbc7f4f8c",
  "description": "xe đạp cực vip",
  "name": "Hehe",
  "name_lower": "hehe",
  "isDelete": false,
  "__v": 0
},{
  "_id": {
    "$oid": "61dc554c368d019deda3771e"
  },
  "cost": 4555,
  "image": "https://cdn.bandeck.com/f95fef10142c4c469b9c17c5a8be6d8a",
  "description": "Dep",
  "name": "aaa",
  "name_lower": "aaa",
  "isDelete": false,
  "__v": 0
},{
  "_id": {
    "$oid": "61dc5773e880adac200d3561"
  },
  "cost": 555,
  "image": "hello",
  "description": "dgdgd",
  "name": "kdldld",
  "name_lower": "kdldld",
  "isDelete": true,
  "__v": 0
},{
  "_id": {
    "$oid": "61dc5936e880adac200d3571"
  },
  "cost": 5555,
  "image": "37d0e544e1425f84c2bdcf7ed9ad904b",
  "description": "kjdjjdsksd",
  "name": "jdkjdkjd",
  "name_lower": "jdkjdkjd",
  "isDelete": true,
  "__v": 0
},{
  "_id": {
    "$oid": "61dc5983e880adac200d3579"
  },
  "cost": 55444,
  "image": "a4f061c400be0ac64536718a882bab5d",
  "description": "kdkdkdk",
  "name": "ksdsdklsd",
  "name_lower": "ksdsdklsd",
  "isDelete": true,
  "__v": 0
},{
  "_id": {
    "$oid": "61dc59c8e880adac200d3581"
  },
  "cost": 2255664,
  "image": "8698431ae4a94e19a75dbb1834a21504",
  "description": "kjdkdkdkd",
  "name": "Xe xinj",
  "name_lower": "xe xinj",
  "isDelete": true,
  "__v": 0
},{
  "_id": {
    "$oid": "61dc5a70e880adac200d35c4"
  },
  "cost": 5555,
  "image": "https://cdn.bandeck.com/6b072379faf1336a59e8054a888970cc",
  "description": "Oke nha",
  "name": "Xe moi",
  "name_lower": "xe moi",
  "isDelete": false,
  "__v": 0
},{
  "_id": {
    "$oid": "61dc5bbee880adac200d7a8f"
  },
  "cost": 4444,
  "image": "https://cdn.bandeck.com/cf5ea844bbd03e43da82819c2dc629a8",
  "description": "Hele",
  "name": "Xe hinj",
  "name_lower": "xe hinj",
  "isDelete": false,
  "__v": 0
},{
  "_id": {
    "$oid": "61dc5c9ee880adac200da956"
  },
  "cost": 555,
  "image": "https://cdn.bandeck.com/ad2ed7d7978025420783132d044a5d25",
  "description": "ddkdkd",
  "name": "dddddd444",
  "name_lower": "dddddd444",
  "isDelete": false,
  "__v": 0
},{
  "_id": {
    "$oid": "61dc5cdbe880adac200dba7a"
  },
  "cost": 555,
  "image": "https://cdn.bandeck.com/46ce2fca55898f667d8740a7894b9281",
  "description": "dddd",
  "name": "aa",
  "name_lower": "aa",
  "isDelete": false,
  "__v": 0
},{
  "_id": {
    "$oid": "61dc5d72e880adac200dd453"
  },
  "cost": 555,
  "image": "https://cdn.bandeck.com/8ea557034864fa4a9a16a70c084114f3",
  "description": "dddd",
  "name": "aa",
  "name_lower": "aa",
  "isDelete": false,
  "__v": 0
},{
  "_id": {
    "$oid": "61dc5e70e880adac200e12cf"
  },
  "cost": 555,
  "image": "https://cdn.bandeck.com/39594298ba0df4b55853e1171e62f598",
  "description": "dddd",
  "name": "aa",
  "name_lower": "aa",
  "isDelete": false,
  "__v": 0
},{
  "_id": {
    "$oid": "61dc63c2d8d9702613a25a6c"
  },
  "cost": 444,
  "image": "https://cdn.bandeck.com/fd4711c1ba86a0ecd3e7bf97eb0272ea",
  "description": "kdkđ",
  "name": "oke",
  "name_lower": "oke",
  "isDelete": true,
  "__v": 0
},{
  "_id": {
    "$oid": "61dc653ed8d9702613a2abf9"
  },
  "cost": 444,
  "image": "https://cdn.bandeck.com/5f4e75ee22b6d309a1507c514b35522e",
  "description": "Nhìn cũng chất phết",
  "name": "sdssđ",
  "name_lower": "sdssđ",
  "isDelete": false,
  "__v": 0
},{
  "_id": {
    "$oid": "6214f86764831fea8292317c"
  },
  "cost": 120000,
  "image": "https://cdn.bandeck.com/fdf7ec09f7e3f779fabb10ab98914f00",
  "description": "cha co gi",
  "name": "ahibi",
  "name_lower": "ahibi",
  "isDelete": false,
  "__v": 0
},{
  "_id": {
    "$oid": "621761caf485f40366614ca0"
  },
  "cost": 120000,
  "image": "https://cdn.bandeck.com/b256704d4b29847c435ef786af1d0e9b",
  "description": "được của ló",
  "name": "ahihi ",
  "name_lower": "ahihi ",
  "isDelete": false,
  "__v": 0
}]